{
  "type": "FeatureCollection",
  "features": [
     {
      "type": "Feature",
      "geometry": {
        "type": "Polygon",
        "coordinates": [
          [
            [
              -2192.37,
              10896.64
            ],
            [
              -1627.49,
              7509.39
            ],
            [
              -647.37,
              12054.76
            ],
            [
              -2192.37,
              10896.64
            ]
          ]
        ]
      },
      "properties": {
        "interpolation": "cspline"
      }
    },
    {
      "type": "Feature",
      "geometry": {
        "type": "Polygon",
        "coordinates": [
          [
            [
              -3298.75,
              5730.73
            ],
            [
              -1298.75,
              5730.73
            ],
            [
              -2060.6,
              7444.23
            ],
            [
              -3298.75,
              5730.73
            ]
          ]
        ]
      },
      "properties": {
        "name": "Triangle!",
        "interpolation": "cspline"
      },
      "id": "triangle"
    }
  ]
}
